setup.cfg
setup.py
extreme_serious_toaster/_init_.py
extreme_serious_toaster.egg-info/PKG-INFO
extreme_serious_toaster.egg-info/SOURCES.txt
extreme_serious_toaster.egg-info/dependency_links.txt
extreme_serious_toaster.egg-info/not-zip-safe
extreme_serious_toaster.egg-info/top_level.txt