Metadata-Version: 2.1
Name: extreme_serious_toaster
Version: 0.0
Summary: Extreme serious toaster for streamlit
Author-email: toupitsyn@gmail.com
